gmail_wrapper/__init__.py
gmail_wrapper/client.py
gmail_wrapper/entities.py
gmail_wrapper/exceptions.py
gmail_wrapper-2.0.0.dist-info/LICENSE
gmail_wrapper-2.0.0.dist-info/METADATA
gmail_wrapper-2.0.0.dist-info/WHEEL
gmail_wrapper-2.0.0.dist-info/top_level.txt
gmail_wrapper-2.0.0.dist-info/RECORD
