Metadata-Version: 2.1
Name: gmail-wrapper
Version: 2.0.0
Summary: Because scrapping Gmail data doesn't have to be a pain
Home-page: https://github.com/loadsmart/gmail-wrapper
Author: Loadsmart Inc.
Author-email: engineering@loadsmart.com
Keywords: gmail
Classifier: Natural Language :: English
Classifier: Programming Language :: Python :: 3
Classifier: Programming Language :: Python :: 3.7
Classifier: Programming Language :: Python :: 3.8
Classifier: Programming Language :: Python :: 3.9
Classifier: Programming Language :: Python :: 3.10
Classifier: Programming Language :: Python :: 3.11
Classifier: Programming Language :: Python :: 3.12
License-File: LICENSE
Requires-Dist: requests <3,>2
Requires-Dist: google-auth-httplib2 <1
Requires-Dist: google-api-python-client <2,>1
Requires-Dist: google-auth <2,>1
